{
  "_class": "symbolInstance",
  "booleanOperation": 0,
  "do_objectID": "3C44190B-7B79-4FCD-9B49-00F22BB13C80",
  "exportOptions": {
    "_class": "exportOptions",
    "do_objectID": "98608528-B12D-49ED-8BCA-6D97C6387B11",
    "exportFormats": [
    ],
    "includedLayerIds": [
    ],
    "layerOptions": 0,
    "shouldTrim": false
  },
  "frame": {
    "_class": "rect",
    "constrainProportions": false,
    "do_objectID": "951CB3F2-2D3A-4715-81D7-C556AC3A859D",
    "height": 344,
    "width": 8,
    "x": 0,
    "y": 0
  },
  "horizontalSpacing": 0,
  "isFixedToViewport": false,
  "isFlippedHorizontal": false,
  "isFlippedVertical": false,
  "isLocked": false,
  "isVisible": true,
  "layerListExpandedType": 0,
  "name": "type",
  "nameIsFixed": true,
  "overrideValues": [
  ],
  "resizingConstraint": 63,
  "resizingType": 0,
  "rotation": 0,
  "scale": 1,
  "shouldBreakMaskChain": false,
  "style": {
    "_class": "style",
    "do_objectID": "221DAD6E-0B62-43CB-831A-BF614BF6D7D7",
    "endMarkerType": 0,
    "miterLimit": 10,
    "startMarkerType": 0,
    "windingRule": 1
  },
  "symbolID": "0A346509-9917-4C58-8F2E-18974D022FD1",
  "verticalSpacing": 0
}