{
  "_class": "text",
  "attributedString": {
    "_class": "attributedString",
    "attributes": [
      {
        "_class": "stringAttribute",
        "attributes": {
          "MSAttributedStringColorAttribute": {
            "_class": "color",
            "alpha": 1,
            "blue": 0.3803921569,
            "green": 0.3803921569,
            "red": 0.3803921569
          },
          "MSAttributedStringFontAttribute": {
            "_class": "fontDescriptor",
            "attributes": {
              "name": "Roboto-Light",
              "size": 14
            }
          },
          "paragraphStyle": {
            "_class": "paragraphStyle",
            "alignment": 0,
            "allowsDefaultTighteningForTruncation": 0,
            "maximumLineHeight": 23,
            "minimumLineHeight": 23
          }
        },
        "length": 15,
        "location": 0
      }
    ],
    "string": "Popover spacing"
  },
  "automaticallyDrawOnUnderlyingPath": false,
  "booleanOperation": 0,
  "do_objectID": "6D0EF620-2DEA-4936-91C7-BE14BC1F8B96",
  "dontSynchroniseWithSymbol": false,
  "exportOptions": {
    "_class": "exportOptions",
    "do_objectID": "D4E84ABA-EBAE-4715-B7D8-D413D7FFCFE0",
    "exportFormats": [
    ],
    "includedLayerIds": [
    ],
    "layerOptions": 0,
    "shouldTrim": false
  },
  "frame": {
    "_class": "rect",
    "constrainProportions": false,
    "do_objectID": "220FDE20-D742-4653-A450-B551CF9BCA09",
    "height": 23,
    "width": 633,
    "x": 327,
    "y": 391
  },
  "glyphBounds": "{{1, 5}, {100, 14}}",
  "isFixedToViewport": false,
  "isFlippedHorizontal": false,
  "isFlippedVertical": false,
  "isLocked": false,
  "isVisible": true,
  "layerListExpandedType": 0,
  "lineSpacingBehaviour": 2,
  "name": "caption copy 2",
  "nameIsFixed": true,
  "originalObjectID": "2271E136-CE0C-4593-9149-A9648A19CC68",
  "resizingConstraint": 42,
  "resizingType": 2,
  "rotation": 0,
  "shouldBreakMaskChain": false,
  "style": {
    "_class": "style",
    "do_objectID": "C6540C9A-A4B7-40AE-9CCB-02C5C1FB3BCF",
    "endMarkerType": 0,
    "miterLimit": 10,
    "startMarkerType": 0,
    "textStyle": {
      "_class": "textStyle",
      "do_objectID": "B461AE79-E78A-4339-BC9C-AFF23C7366FC",
      "encodedAttributes": {
        "MSAttributedStringColorAttribute": {
          "_class": "color",
          "alpha": 1,
          "blue": 0.3803921569,
          "green": 0.3803921569,
          "red": 0.3803921569
        },
        "MSAttributedStringFontAttribute": {
          "_class": "fontDescriptor",
          "attributes": {
            "name": "Roboto-Light",
            "size": 14
          }
        },
        "paragraphStyle": {
          "_class": "paragraphStyle",
          "alignment": 0,
          "allowsDefaultTighteningForTruncation": 0,
          "maximumLineHeight": 23,
          "minimumLineHeight": 23
        }
      },
      "verticalAlignment": 0
    },
    "windingRule": 1
  },
  "textBehaviour": 1
}