{
  "_class": "text",
  "attributedString": {
    "_class": "attributedString",
    "attributes": [
      {
        "_class": "stringAttribute",
        "attributes": {
          "MSAttributedStringColorAttribute": {
            "_class": "color",
            "alpha": 1,
            "blue": 0.2,
            "green": 0.2,
            "red": 0.2
          },
          "MSAttributedStringFontAttribute": {
            "_class": "fontDescriptor",
            "attributes": {
              "name": "Roboto-Regular",
              "size": 14
            }
          },
          "paragraphStyle": {
            "_class": "paragraphStyle",
            "alignment": 0,
            "allowsDefaultTighteningForTruncation": 0,
            "maximumLineHeight": 23,
            "minimumLineHeight": 23
          }
        },
        "length": 640,
        "location": 0
      }
    ],
    "string": "For tectual identifiers, feel free to use whatever textual shorthand makes sense for your user case. In the instance of a Chip for a user, you might consider their first and last name. \n\nFor image identifiers, you’ll want to center the visual interest in the 40x40 chip container to that the chip can be properly identified. It is best to make sure the detail of the image is discernable at that size. \n\nFor iconic identifiers, use a white background and an icon that does not touch the borders of the container itself – there should be at least 1px of gap between the icon and the border. The outline inherits the color of the icon itself."
  },
  "automaticallyDrawOnUnderlyingPath": false,
  "booleanOperation": 0,
  "do_objectID": "380DEDCC-EECA-4506-924F-C7E28D8C4EED",
  "dontSynchroniseWithSymbol": false,
  "exportOptions": {
    "_class": "exportOptions",
    "do_objectID": "DD7CE5F2-A1C4-4F04-847F-8C4EB7BE22C0",
    "exportFormats": [
    ],
    "includedLayerIds": [
    ],
    "layerOptions": 0,
    "shouldTrim": false
  },
  "frame": {
    "_class": "rect",
    "constrainProportions": false,
    "do_objectID": "C5ACA30D-B8AD-4920-8880-4C889C08711F",
    "height": 368,
    "width": 305,
    "x": 32,
    "y": 1418
  },
  "glyphBounds": "{{0, 5}, {304, 357}}",
  "isFixedToViewport": false,
  "isFlippedHorizontal": false,
  "isFlippedVertical": false,
  "isLocked": false,
  "isVisible": true,
  "layerListExpandedType": 0,
  "lineSpacingBehaviour": 2,
  "name": "description",
  "nameIsFixed": true,
  "resizingConstraint": 18,
  "resizingType": 2,
  "rotation": 0,
  "shouldBreakMaskChain": false,
  "style": {
    "_class": "style",
    "do_objectID": "60F8D7A8-E2A1-4976-A18B-965BD5B09F2F",
    "endMarkerType": 0,
    "miterLimit": 10,
    "startMarkerType": 0,
    "textStyle": {
      "_class": "textStyle",
      "do_objectID": "3D1A5488-6252-4DEB-93DF-82721D1D6503",
      "encodedAttributes": {
        "MSAttributedStringColorAttribute": {
          "_class": "color",
          "alpha": 1,
          "blue": 0.2,
          "green": 0.2,
          "red": 0.2
        },
        "MSAttributedStringFontAttribute": {
          "_class": "fontDescriptor",
          "attributes": {
            "name": "Roboto-Regular",
            "size": 14
          }
        },
        "paragraphStyle": {
          "_class": "paragraphStyle",
          "alignment": 0,
          "allowsDefaultTighteningForTruncation": 0,
          "maximumLineHeight": 23,
          "minimumLineHeight": 23
        }
      },
      "verticalAlignment": 0
    },
    "windingRule": 1
  },
  "textBehaviour": 1,
  "userInfo": {
    "com.animaapp.stc-sketch-plugin": {
      "kModelPropertiesKey": {
        "isAutoWidth": 0
      }
    }
  }
}