{
  "_class": "symbolInstance",
  "booleanOperation": 0,
  "do_objectID": "C7618A17-F9FE-4655-9095-0CD03CE3866F",
  "exportOptions": {
    "_class": "exportOptions",
    "do_objectID": "CFEA56C0-CE01-4087-BF49-E825974A9A8F",
    "exportFormats": [
    ],
    "includedLayerIds": [
    ],
    "layerOptions": 0,
    "shouldTrim": false
  },
  "frame": {
    "_class": "rect",
    "constrainProportions": false,
    "do_objectID": "159EF497-18EA-44C8-8FA9-A393BB4B64D1",
    "height": 90.21301775147931,
    "width": 121,
    "x": 0,
    "y": 0
  },
  "horizontalSpacing": 0,
  "isFixedToViewport": false,
  "isFlippedHorizontal": false,
  "isFlippedVertical": false,
  "isLocked": false,
  "isVisible": true,
  "layerListExpandedType": 0,
  "name": "Card / Stage",
  "nameIsFixed": false,
  "originalObjectID": "81ED6462-7D22-4488-8626-F463B89A2042",
  "overrideValues": [
  ],
  "resizingConstraint": 63,
  "resizingType": 0,
  "rotation": 0,
  "scale": 1,
  "shouldBreakMaskChain": false,
  "style": {
    "_class": "style",
    "do_objectID": "A390FAC6-23F9-48F5-9040-1DB2FFE6E30C",
    "endMarkerType": 0,
    "miterLimit": 10,
    "startMarkerType": 0,
    "windingRule": 1
  },
  "symbolID": "7F724B74-E4AC-46EB-9C4E-5987C6A66BDE",
  "verticalSpacing": 0
}