{
  "_class": "symbolInstance",
  "booleanOperation": 0,
  "do_objectID": "3E1AEAA4-8101-486A-9BA8-51665A282D1A",
  "exportOptions": {
    "_class": "exportOptions",
    "exportFormats": [
    ],
    "includedLayerIds": [
    ],
    "layerOptions": 0,
    "shouldTrim": false
  },
  "frame": {
    "_class": "rect",
    "constrainProportions": false,
    "height": 72,
    "width": 375,
    "x": 1,
    "y": 1
  },
  "horizontalSpacing": 0,
  "isFixedToViewport": false,
  "isFlippedHorizontal": false,
  "isFlippedVertical": false,
  "isLocked": false,
  "isVisible": true,
  "layerListExpandedType": 0,
  "name": "Padding",
  "nameIsFixed": true,
  "originalObjectID": "EA1C23E3-56B8-4C3F-9864-E227DCCEBE0D",
  "overrideValues": [
  ],
  "resizingConstraint": 18,
  "resizingType": 0,
  "rotation": 0,
  "scale": 1,
  "shouldBreakMaskChain": false,
  "style": {
    "_class": "style",
    "endMarkerType": 0,
    "miterLimit": 10,
    "startMarkerType": 0,
    "windingRule": 1
  },
  "symbolID": "585BD1C5-CEF9-4BF6-B15D-3EEFF68ECEFA",
  "verticalSpacing": 0
}