{
  "_class": "group",
  "booleanOperation": 0,
  "do_objectID": "918318CF-7CD3-4476-A7C4-D9BF0B1582A4",
  "exportOptions": {
    "_class": "exportOptions",
    "do_objectID": "F20DD58A-B38F-44C9-BFD1-5BD9D2A6595B",
    "exportFormats": [
    ],
    "includedLayerIds": [
    ],
    "layerOptions": 0,
    "shouldTrim": false
  },
  "frame": {
    "_class": "rect",
    "constrainProportions": false,
    "do_objectID": "8BA101C8-71CF-4904-B649-EC41AF305103",
    "height": 58,
    "width": 255,
    "x": 0,
    "y": 0
  },
  "hasClickThrough": false,
  "isFixedToViewport": false,
  "isFlippedHorizontal": false,
  "isFlippedVertical": false,
  "isLocked": false,
  "isVisible": true,
  "layerListExpandedType": 0,
  "layers": [
    {
      "class": "shapeGroup",
      "id": "2D036667-251C-4266-8D67-01B533893048"
    }
  ],
  "name": "container",
  "nameIsFixed": true,
  "resizingConstraint": 63,
  "resizingType": 0,
  "rotation": 0,
  "shouldBreakMaskChain": false,
  "style": {
    "_class": "style",
    "do_objectID": "9F44A6A0-2305-4710-91D1-4164BFBCF1C9",
    "endMarkerType": 0,
    "miterLimit": 10,
    "startMarkerType": 0,
    "windingRule": 1
  }
}