{
  "_class": "text",
  "attributedString": {
    "_class": "attributedString",
    "attributes": [
      {
        "_class": "stringAttribute",
        "attributes": {
          "MSAttributedStringColorAttribute": {
            "_class": "color",
            "alpha": 1,
            "blue": 0.259,
            "green": 0.259,
            "red": 0.259
          },
          "MSAttributedStringFontAttribute": {
            "_class": "fontDescriptor",
            "attributes": {
              "name": "Roboto-Regular",
              "size": 24
            }
          },
          "paragraphStyle": {
            "_class": "paragraphStyle",
            "maximumLineHeight": 36,
            "minimumLineHeight": 36
          }
        },
        "length": 7,
        "location": 0
      }
    ],
    "string": "Account"
  },
  "automaticallyDrawOnUnderlyingPath": false,
  "booleanOperation": 0,
  "do_objectID": "7CE644E7-023A-4A59-B226-671C0C76ED70",
  "dontSynchroniseWithSymbol": false,
  "exportOptions": {
    "_class": "exportOptions",
    "do_objectID": "5FE2606D-0141-41B9-ADBA-163B9356B50A",
    "exportFormats": [
    ],
    "includedLayerIds": [
    ],
    "layerOptions": 0,
    "shouldTrim": false
  },
  "frame": {
    "_class": "rect",
    "constrainProportions": false,
    "do_objectID": "4ECE9045-CD5C-4A6B-B306-4A39DC2AE58B",
    "height": 36,
    "width": 89,
    "x": 52,
    "y": 0
  },
  "glyphBounds": "{{0, 8}, {88, 19}}",
  "isFixedToViewport": false,
  "isFlippedHorizontal": false,
  "isFlippedVertical": false,
  "isLocked": false,
  "isVisible": true,
  "layerListExpandedType": 0,
  "lineSpacingBehaviour": 2,
  "name": "Account Copy",
  "nameIsFixed": false,
  "resizingConstraint": 47,
  "resizingType": 0,
  "rotation": 0,
  "shouldBreakMaskChain": false,
  "style": {
    "_class": "style",
    "do_objectID": "7DE44CE0-45D6-4CFA-8F00-680ADD324559",
    "endMarkerType": 0,
    "miterLimit": 10,
    "sharedObjectID": "1BF757B1-280E-40DF-BE43-5E7EF6F24D2A",
    "startMarkerType": 0,
    "textStyle": {
      "_class": "textStyle",
      "do_objectID": "8C66C8A6-0CDD-476D-9016-E289B2315C39",
      "encodedAttributes": {
        "MSAttributedStringColorAttribute": {
          "_class": "color",
          "alpha": 1,
          "blue": 0.259,
          "green": 0.259,
          "red": 0.259
        },
        "MSAttributedStringFontAttribute": {
          "_class": "fontDescriptor",
          "attributes": {
            "name": "Roboto-Regular",
            "size": 24
          }
        },
        "paragraphStyle": {
          "_class": "paragraphStyle",
          "maximumLineHeight": 36,
          "minimumLineHeight": 36
        }
      },
      "verticalAlignment": 0
    },
    "windingRule": 1
  },
  "textBehaviour": 0
}