{
  "_class": "group",
  "booleanOperation": 0,
  "do_objectID": "0098463F-F760-48A5-AB9E-7A611A3FF48E",
  "exportOptions": {
    "_class": "exportOptions",
    "do_objectID": "5A6818A7-E6B5-4378-97C8-5D1A6B07F790",
    "exportFormats": [
    ],
    "includedLayerIds": [
    ],
    "layerOptions": 0,
    "shouldTrim": false
  },
  "frame": {
    "_class": "rect",
    "constrainProportions": false,
    "do_objectID": "7DB75D77-FE20-4693-86E2-1B9D5476A37D",
    "height": 36,
    "width": 36,
    "x": 0,
    "y": 0
  },
  "hasClickThrough": false,
  "isFixedToViewport": false,
  "isFlippedHorizontal": false,
  "isFlippedVertical": false,
  "isLocked": false,
  "isVisible": true,
  "layerListExpandedType": 0,
  "layers": [
    {
      "class": "shapeGroup",
      "id": "FD427C1F-1C3D-491B-8FF2-1B51A543D9D2"
    },
    {
      "class": "shapeGroup",
      "id": "1A5D0332-EEA4-40EE-9CE7-306383AE51CE"
    }
  ],
  "name": "Group 51",
  "nameIsFixed": false,
  "resizingConstraint": 63,
  "resizingType": 0,
  "rotation": 0,
  "shouldBreakMaskChain": false,
  "style": {
    "_class": "style",
    "do_objectID": "992AD942-0B20-4C72-A04A-9582F99B9E4E",
    "endMarkerType": 0,
    "miterLimit": 10,
    "startMarkerType": 0,
    "windingRule": 1
  }
}