{
  "_class": "symbolInstance",
  "booleanOperation": 0,
  "do_objectID": "7AB123AF-74BB-4D84-9B03-71FEE8B9BE55",
  "exportOptions": {
    "_class": "exportOptions",
    "do_objectID": "DF890DDA-6F7E-4078-A292-1E5C1645A018",
    "exportFormats": [
    ],
    "includedLayerIds": [
    ],
    "layerOptions": 0,
    "shouldTrim": false
  },
  "frame": {
    "_class": "rect",
    "constrainProportions": false,
    "do_objectID": "278F4AD3-0855-449A-A917-8F389D367FF9",
    "height": 12,
    "width": 240,
    "x": 283,
    "y": 114
  },
  "horizontalSpacing": 0,
  "isFixedToViewport": false,
  "isFlippedHorizontal": true,
  "isFlippedVertical": false,
  "isLocked": false,
  "isVisible": true,
  "layerListExpandedType": 0,
  "name": "redlines/line/straight copy 14",
  "nameIsFixed": false,
  "overrideValues": [
    {
      "_class": "overrideValue",
      "do_objectID": "90C878E1-1C34-46C4-BA2C-2DCBE6F3715C",
      "overrideName": "2A45B77A-DE22-4C3C-91F9-F5095CA78E2B_symbolID",
      "value": "96843202-F1BE-4A3B-B404-E8AC48C79BB0"
    },
    {
      "_class": "overrideValue",
      "do_objectID": "EFDDFD38-BA16-4645-837C-4EB70516830C",
      "overrideName": "4664D1EE-D53D-4C47-AF10-700B98C5C8BC_symbolID",
      "value": "72515AF1-2F45-478C-B373-014FFF58A451"
    }
  ],
  "resizingConstraint": 63,
  "resizingType": 0,
  "rotation": 0,
  "scale": 1,
  "shouldBreakMaskChain": false,
  "style": {
    "_class": "style",
    "do_objectID": "9068D3FD-F458-405A-BE82-799A90D1DE4A",
    "endMarkerType": 0,
    "miterLimit": 10,
    "startMarkerType": 0,
    "windingRule": 1
  },
  "symbolID": "14383C59-F874-4BAA-8595-131A3C5C22CF",
  "verticalSpacing": 0
}